.coveragerc
AUTHORS.rst
CHANGES.rst
LICENSE.txt
README.rst
requirements.txt
setup.cfg
setup.py
test-requirements.txt
docs/Makefile
docs/authors.rst
docs/changes.rst
docs/conf.py
docs/index.rst
docs/license.rst
docs/_static/.gitignore
notebooks/analyse_performance.ipynb
tests/conftest.py
zipline_poloniex/__init__.py
zipline_poloniex/api.py
zipline_poloniex/bundle.py
zipline_poloniex/dummy_agent.py
zipline_poloniex/utils.py
zipline_poloniex.egg-info/PKG-INFO
zipline_poloniex.egg-info/SOURCES.txt
zipline_poloniex.egg-info/dependency_links.txt
zipline_poloniex.egg-info/not-zip-safe
zipline_poloniex.egg-info/requires.txt
zipline_poloniex.egg-info/top_level.txt