Metadata-Version: 1.1
Name: zipline-poloniex
Version: 0.1.1
Summary: Poloniex data bundle for zipline, the pythonic algorithmic trading library.
Home-page: https://github.com/FlorianWilhelm/zipline-poloniex
Author: Florian Wilhelm
Author-email: florian.wilhelm@gmail.com
License: new-bsd
Platform: UNKNOWN
Classifier: Development Status :: 4 - Beta
Classifier: Programming Language :: Python
